{
  "Alan": {
    "2026-04-05": {
      "units": {
        "score": 60,
        "correct": 6,
        "wrong": 0
      },
      "english": {
        "score": 80,
        "correct": 8,
        "wrong": 3
      }
    }
  },
  "test": {
    "2026-04-05": {
      "clock": {
        "score": 10,
        "correct": 1,
        "wrong": 0
      }
    }
  },
  "孙慕轩": {
    "2026-04-05": {
      "units": {
        "score": 240,
        "correct": 24,
        "wrong": 17
      },
      "english": {
        "score": 30,
        "correct": 3,
        "wrong": 2
      }
    }
  },
  "叶一男": {
    "2026-04-05": {
      "units": {
        "score": 20,
        "correct": 2,
        "wrong": 1
      }
    }
  }
}